Workbook

Sheet Tổng quan
A1: Starlyn – Retest lượt 2 (06/10/2026)
A2: Test funnel.html sau commit fix 47087fd (+ thay đổi chưa commit lúc 17:11) · 375×667 + 430×932 · cả 10 funnel đi thật tới paywall không lỗi JS · Tester: Claude Code
A4: Funnel | B4: Bug cũ | C4: Fixed | D4: Partly fixed | E4: Cần PM | F4: Not fixed | G4: Bug mới | H4: Mới: High | I4: Mới: Medium | J4: Mới: Low | K4: Đang mở
A5: astrocartography | B5: =COUNTIF('Retest bug cũ'!$A$2:$A$118,$A5) | C5: =COUNTIFS('Retest bug cũ'!$A$2:$A$118,$A5,'Retest bug cũ'!$F$2:$F$118,"Fixed") | D5: =COUNTIFS('Retest bug cũ'!$A$2:$A$118,$A5,'Retest bug cũ'!$F$2:$F$118,"Partly fixed") | E5: =COUNTIFS('Retest bug cũ'!$A$2:$A$118,$A5,'Retest bug cũ'!$F$2:$F$118,"Cần PM") | F5: =COUNTIFS('Retest bug cũ'!$A$2:$A$118,$A5,'Retest bug cũ'!$F$2:$F$118,"Not fixed") | G5: =COUNTIFS('Bug đang mở'!$B$2:$B$41,$A5,'Bug đang mở'!$E$2:$E$41,"Bug mới") | H5: =COUNTIFS('Bug đang mở'!$B$2:$B$41,$A5,'Bug đang mở'!$E$2:$E$41,"Bug mới",'Bug đang mở'!$D$2:$D$41,"High") | I5: =COUNTIFS('Bug đang mở'!$B$2:$B$41,$A5,'Bug đang mở'!$E$2:$E$41,"Bug mới",'Bug đang mở'!$D$2:$D$41,"Medium") | J5: =COUNTIFS('Bug đang mở'!$B$2:$B$41,$A5,'Bug đang mở'!$E$2:$E$41,"Bug mới",'Bug đang mở'!$D$2:$D$41,"Low") | K5: =COUNTIF('Bug đang mở'!$B$2:$B$41,$A5)
A6: aura-tarot | B6: =COUNTIF('Retest bug cũ'!$A$2:$A$118,$A6) | C6: =COUNTIFS('Retest bug cũ'!$A$2:$A$118,$A6,'Retest bug cũ'!$F$2:$F$118,"Fixed") | D6: =COUNTIFS('Retest bug cũ'!$A$2:$A$118,$A6,'Retest bug cũ'!$F$2:$F$118,"Partly fixed") | E6: =COUNTIFS('Retest bug cũ'!$A$2:$A$118,$A6,'Retest bug cũ'!$F$2:$F$118,"Cần PM") | F6: =COUNTIFS('Retest bug cũ'!$A$2:$A$118,$A6,'Retest bug cũ'!$F$2:$F$118,"Not fixed") | G6: =COUNTIFS('Bug đang mở'!$B$2:$B$41,$A6,'Bug đang mở'!$E$2:$E$41,"Bug mới") | H6: =COUNTIFS('Bug đang mở'!$B$2:$B$41,$A6,'Bug đang mở'!$E$2:$E$41,"Bug mới",'Bug đang mở'!$D$2:$D$41,"High") | I6: =COUNTIFS('Bug đang mở'!$B$2:$B$41,$A6,'Bug đang mở'!$E$2:$E$41,"Bug mới",'Bug đang mở'!$D$2:$D$41,"Medium") | J6: =COUNTIFS('Bug đang mở'!$B$2:$B$41,$A6,'Bug đang mở'!$E$2:$E$41,"Bug mới",'Bug đang mở'!$D$2:$D$41,"Low") | K6: =COUNTIF('Bug đang mở'!$B$2:$B$41,$A6)
A7: ex-compatibility | B7: =COUNTIF('Retest bug cũ'!$A$2:$A$118,$A7) | C7: =COUNTIFS('Retest bug cũ'!$A$2:$A$118,$A7,'Retest bug cũ'!$F$2:$F$118,"Fixed") | D7: =COUNTIFS('Retest bug cũ'!$A$2:$A$118,$A7,'Retest bug cũ'!$F$2:$F$118,"Partly fixed") | E7: =COUNTIFS('Retest bug cũ'!$A$2:$A$118,$A7,'Retest bug cũ'!$F$2:$F$118,"Cần PM") | F7: =COUNTIFS('Retest bug cũ'!$A$2:$A$118,$A7,'Retest bug cũ'!$F$2:$F$118,"Not fixed") | G7: =COUNTIFS('Bug đang mở'!$B$2:$B$41,$A7,'Bug đang mở'!$E$2:$E$41,"Bug mới") | H7: =COUNTIFS('Bug đang mở'!$B$2:$B$41,$A7,'Bug đang mở'!$E$2:$E$41,"Bug mới",'Bug đang mở'!$D$2:$D$41,"High") | I7: =COUNTIFS('Bug đang mở'!$B$2:$B$41,$A7,'Bug đang mở'!$E$2:$E$41,"Bug mới",'Bug đang mở'!$D$2:$D$41,"Medium") | J7: =COUNTIFS('Bug đang mở'!$B$2:$B$41,$A7,'Bug đang mở'!$E$2:$E$41,"Bug mới",'Bug đang mở'!$D$2:$D$41,"Low") | K7: =COUNTIF('Bug đang mở'!$B$2:$B$41,$A7)
A8: marriage-compatibility | B8: =COUNTIF('Retest bug cũ'!$A$2:$A$118,$A8) | C8: =COUNTIFS('Retest bug cũ'!$A$2:$A$118,$A8,'Retest bug cũ'!$F$2:$F$118,"Fixed") | D8: =COUNTIFS('Retest bug cũ'!$A$2:$A$118,$A8,'Retest bug cũ'!$F$2:$F$118,"Partly fixed") | E8: =COUNTIFS('Retest bug cũ'!$A$2:$A$118,$A8,'Retest bug cũ'!$F$2:$F$118,"Cần PM") | F8: =COUNTIFS('Retest bug cũ'!$A$2:$A$118,$A8,'Retest bug cũ'!$F$2:$F$118,"Not fixed") | G8: =COUNTIFS('Bug đang mở'!$B$2:$B$41,$A8,'Bug đang mở'!$E$2:$E$41,"Bug mới") | H8: =COUNTIFS('Bug đang mở'!$B$2:$B$41,$A8,'Bug đang mở'!$E$2:$E$41,"Bug mới",'Bug đang mở'!$D$2:$D$41,"High") | I8: =COUNTIFS('Bug đang mở'!$B$2:$B$41,$A8,'Bug đang mở'!$E$2:$E$41,"Bug mới",'Bug đang mở'!$D$2:$D$41,"Medium") | J8: =COUNTIFS('Bug đang mở'!$B$2:$B$41,$A8,'Bug đang mở'!$E$2:$E$41,"Bug mới",'Bug đang mở'!$D$2:$D$41,"Low") | K8: =COUNTIF('Bug đang mở'!$B$2:$B$41,$A8)
A9: moon-reading | B9: =COUNTIF('Retest bug cũ'!$A$2:$A$118,$A9) | C9: =COUNTIFS('Retest bug cũ'!$A$2:$A$118,$A9,'Retest bug cũ'!$F$2:$F$118,"Fixed") | D9: =COUNTIFS('Retest bug cũ'!$A$2:$A$118,$A9,'Retest bug cũ'!$F$2:$F$118,"Partly fixed") | E9: =COUNTIFS('Retest bug cũ'!$A$2:$A$118,$A9,'Retest bug cũ'!$F$2:$F$118,"Cần PM") | F9: =COUNTIFS('Retest bug cũ'!$A$2:$A$118,$A9,'Retest bug cũ'!$F$2:$F$118,"Not fixed") | G9: =COUNTIFS('Bug đang mở'!$B$2:$B$41,$A9,'Bug đang mở'!$E$2:$E$41,"Bug mới") | H9: =COUNTIFS('Bug đang mở'!$B$2:$B$41,$A9,'Bug đang mở'!$E$2:$E$41,"Bug mới",'Bug đang mở'!$D$2:$D$41,"High") | I9: =COUNTIFS('Bug đang mở'!$B$2:$B$41,$A9,'Bug đang mở'!$E$2:$E$41,"Bug mới",'Bug đang mở'!$D$2:$D$41,"Medium") | J9: =COUNTIFS('Bug đang mở'!$B$2:$B$41,$A9,'Bug đang mở'!$E$2:$E$41,"Bug mới",'Bug đang mở'!$D$2:$D$41,"Low") | K9: =COUNTIF('Bug đang mở'!$B$2:$B$41,$A9)
A10: palm-reading | B10: =COUNTIF('Retest bug cũ'!$A$2:$A$118,$A10) | C10: =COUNTIFS('Retest bug cũ'!$A$2:$A$118,$A10,'Retest bug cũ'!$F$2:$F$118,"Fixed") | D10: =COUNTIFS('Retest bug cũ'!$A$2:$A$118,$A10,'Retest bug cũ'!$F$2:$F$118,"Partly fixed") | E10: =COUNTIFS('Retest bug cũ'!$A$2:$A$118,$A10,'Retest bug cũ'!$F$2:$F$118,"Cần PM") | F10: =COUNTIFS('Retest bug cũ'!$A$2:$A$118,$A10,'Retest bug cũ'!$F$2:$F$118,"Not fixed") | G10: =COUNTIFS('Bug đang mở'!$B$2:$B$41,$A10,'Bug đang mở'!$E$2:$E$41,"Bug mới") | H10: =COUNTIFS('Bug đang mở'!$B$2:$B$41,$A10,'Bug đang mở'!$E$2:$E$41,"Bug mới",'Bug đang mở'!$D$2:$D$41,"High") | I10: =COUNTIFS('Bug đang mở'!$B$2:$B$41,$A10,'Bug đang mở'!$E$2:$E$41,"Bug mới",'Bug đang mở'!$D$2:$D$41,"Medium") | J10: =COUNTIFS('Bug đang mở'!$B$2:$B$41,$A10,'Bug đang mở'!$E$2:$E$41,"Bug mới",'Bug đang mở'!$D$2:$D$41,"Low") | K10: =COUNTIF('Bug đang mở'!$B$2:$B$41,$A10)
A11: past-life | B11: =COUNTIF('Retest bug cũ'!$A$2:$A$118,$A11) | C11: =COUNTIFS('Retest bug cũ'!$A$2:$A$118,$A11,'Retest bug cũ'!$F$2:$F$118,"Fixed") | D11: =COUNTIFS('Retest bug cũ'!$A$2:$A$118,$A11,'Retest bug cũ'!$F$2:$F$118,"Partly fixed") | E11: =COUNTIFS('Retest bug cũ'!$A$2:$A$118,$A11,'Retest bug cũ'!$F$2:$F$118,"Cần PM") | F11: =COUNTIFS('Retest bug cũ'!$A$2:$A$118,$A11,'Retest bug cũ'!$F$2:$F$118,"Not fixed") | G11: =COUNTIFS('Bug đang mở'!$B$2:$B$41,$A11,'Bug đang mở'!$E$2:$E$41,"Bug mới") | H11: =COUNTIFS('Bug đang mở'!$B$2:$B$41,$A11,'Bug đang mở'!$E$2:$E$41,"Bug mới",'Bug đang mở'!$D$2:$D$41,"High") | I11: =COUNTIFS('Bug đang mở'!$B$2:$B$41,$A11,'Bug đang mở'!$E$2:$E$41,"Bug mới",'Bug đang mở'!$D$2:$D$41,"Medium") | J11: =COUNTIFS('Bug đang mở'!$B$2:$B$41,$A11,'Bug đang mở'!$E$2:$E$41,"Bug mới",'Bug đang mở'!$D$2:$D$41,"Low") | K11: =COUNTIF('Bug đang mở'!$B$2:$B$41,$A11)
A12: soulmate-sketch | B12: =COUNTIF('Retest bug cũ'!$A$2:$A$118,$A12) | C12: =COUNTIFS('Retest bug cũ'!$A$2:$A$118,$A12,'Retest bug cũ'!$F$2:$F$118,"Fixed") | D12: =COUNTIFS('Retest bug cũ'!$A$2:$A$118,$A12,'Retest bug cũ'!$F$2:$F$118,"Partly fixed") | E12: =COUNTIFS('Retest bug cũ'!$A$2:$A$118,$A12,'Retest bug cũ'!$F$2:$F$118,"Cần PM") | F12: =COUNTIFS('Retest bug cũ'!$A$2:$A$118,$A12,'Retest bug cũ'!$F$2:$F$118,"Not fixed") | G12: =COUNTIFS('Bug đang mở'!$B$2:$B$41,$A12,'Bug đang mở'!$E$2:$E$41,"Bug mới") | H12: =COUNTIFS('Bug đang mở'!$B$2:$B$41,$A12,'Bug đang mở'!$E$2:$E$41,"Bug mới",'Bug đang mở'!$D$2:$D$41,"High") | I12: =COUNTIFS('Bug đang mở'!$B$2:$B$41,$A12,'Bug đang mở'!$E$2:$E$41,"Bug mới",'Bug đang mở'!$D$2:$D$41,"Medium") | J12: =COUNTIFS('Bug đang mở'!$B$2:$B$41,$A12,'Bug đang mở'!$E$2:$E$41,"Bug mới",'Bug đang mở'!$D$2:$D$41,"Low") | K12: =COUNTIF('Bug đang mở'!$B$2:$B$41,$A12)
A13: tarot | B13: =COUNTIF('Retest bug cũ'!$A$2:$A$118,$A13) | C13: =COUNTIFS('Retest bug cũ'!$A$2:$A$118,$A13,'Retest bug cũ'!$F$2:$F$118,"Fixed") | D13: =COUNTIFS('Retest bug cũ'!$A$2:$A$118,$A13,'Retest bug cũ'!$F$2:$F$118,"Partly fixed") | E13: =COUNTIFS('Retest bug cũ'!$A$2:$A$118,$A13,'Retest bug cũ'!$F$2:$F$118,"Cần PM") | F13: =COUNTIFS('Retest bug cũ'!$A$2:$A$118,$A13,'Retest bug cũ'!$F$2:$F$118,"Not fixed") | G13: =COUNTIFS('Bug đang mở'!$B$2:$B$41,$A13,'Bug đang mở'!$E$2:$E$41,"Bug mới") | H13: =COUNTIFS('Bug đang mở'!$B$2:$B$41,$A13,'Bug đang mở'!$E$2:$E$41,"Bug mới",'Bug đang mở'!$D$2:$D$41,"High") | I13: =COUNTIFS('Bug đang mở'!$B$2:$B$41,$A13,'Bug đang mở'!$E$2:$E$41,"Bug mới",'Bug đang mở'!$D$2:$D$41,"Medium") | J13: =COUNTIFS('Bug đang mở'!$B$2:$B$41,$A13,'Bug đang mở'!$E$2:$E$41,"Bug mới",'Bug đang mở'!$D$2:$D$41,"Low") | K13: =COUNTIF('Bug đang mở'!$B$2:$B$41,$A13)
A14: witch-power | B14: =COUNTIF('Retest bug cũ'!$A$2:$A$118,$A14) | C14: =COUNTIFS('Retest bug cũ'!$A$2:$A$118,$A14,'Retest bug cũ'!$F$2:$F$118,"Fixed") | D14: =COUNTIFS('Retest bug cũ'!$A$2:$A$118,$A14,'Retest bug cũ'!$F$2:$F$118,"Partly fixed") | E14: =COUNTIFS('Retest bug cũ'!$A$2:$A$118,$A14,'Retest bug cũ'!$F$2:$F$118,"Cần PM") | F14: =COUNTIFS('Retest bug cũ'!$A$2:$A$118,$A14,'Retest bug cũ'!$F$2:$F$118,"Not fixed") | G14: =COUNTIFS('Bug đang mở'!$B$2:$B$41,$A14,'Bug đang mở'!$E$2:$E$41,"Bug mới") | H14: =COUNTIFS('Bug đang mở'!$B$2:$B$41,$A14,'Bug đang mở'!$E$2:$E$41,"Bug mới",'Bug đang mở'!$D$2:$D$41,"High") | I14: =COUNTIFS('Bug đang mở'!$B$2:$B$41,$A14,'Bug đang mở'!$E$2:$E$41,"Bug mới",'Bug đang mở'!$D$2:$D$41,"Medium") | J14: =COUNTIFS('Bug đang mở'!$B$2:$B$41,$A14,'Bug đang mở'!$E$2:$E$41,"Bug mới",'Bug đang mở'!$D$2:$D$41,"Low") | K14: =COUNTIF('Bug đang mở'!$B$2:$B$41,$A14)
A15: Tổng | B15: =SUM(B5:B14) | C15: =SUM(C5:C14) | D15: =SUM(D5:D14) | E15: =SUM(E5:E14) | F15: =SUM(F5:F14) | G15: =SUM(G5:G14) | H15: =SUM(H5:H14) | I15: =SUM(I5:I14) | ... K15: =SUM(K5:K14)

Sheet Retest bug cũ
A1: Funnel | B1: # cũ | C1: Screen | D1: Severity | E1: Title | F1: Status lượt 2 | G1: Ghi chú lượt 2 | H1: Attachment lượt 2
A2: astrocartography | B2: 1 | C2: Intro 1 | D2: High | E2: [UI/UX][Intro 1] Link "Terms" và "Privacy Policy" có tap target quá nhỏ | F2: Fixed | G2: - Link Terms/Privacy Policy đã underline, auto-check lượt 2 không còn cảnh báo tap target nhỏ ở id 1 và id 20 (cả small/large). | H2: Screenshot/Video: screens/01-1-small.png, screens/01-1-large.png, screens/20-20-small.png, screens/20-20-large.png, capture.json
A3: astrocartography | B3: 2 | C3: Intro 1 | D3: Low | E3: [UI][Intro 1] Globe hero không hiển thị các planetary line màu theo spec | F3: Fixed | G3: - Intro 1: globe có 3 line màu (cam, hồng, bạc) chạy qua và chấm vị trí user. Intro 17: line màu đang trace pole-to-pole và có city pin vàng (Chicago) đang ping. Ảnh chụp ở 1.2s (bước 47%) nên mới thấy 1 pin, các pin top 3 xuất hiện lần lượt sau đó (timing animation). Dev ghi Partly fixed, QA thấy đủ yếu tố brief – độ tin cậy trung bình. | H3: Screenshot/Video: screens/01-1-small.png, screens/01-1-large.png, screens/17-17-small.png, screens/17-17-large.png
A4: astrocartography | B4: 3 | C4: Intro 2 | D4: Medium | E4: [UI][Intro 2] Venus và Jupiter hiển thị cùng màu vàng, không phân biệt được line | F4: Fixed | G4: - Venus hiển thị màu hồng (rose), Jupiter vàng, Sun cam, Moon bạc, đồng nhất giữa legend và line ở Intro 2, 4, 9, 18. Intro 2 mới thấy 3/4 chip (thiếu chip Moon) do chip fade-in lần lượt, chip thứ 4 chưa hiện lúc chụp 1.2s – timing, không phải bug. | H4: Screenshot/Video: screens/02-2-small.png, screens/04-4-small.png, screens/09-9-small-p1.png, screens/18-18-small-p1.png
A5: astrocartography | B5: 4 | C5: Intro 5 | D5: Medium | E5: [UI][Intro 5] Label trên map card nằm đè lên lưới chấm bản đồ | F5: Fixed | G5: - Label "test's map" (Intro 5) và "Chicago" (Intro 11) đã có nền pill tối đặc + viền, đọc rõ trên lưới chấm. | H5: Screenshot/Video: screens/05-5-small.png, screens/05-5-large.png, screens/11-11-small.png, screens/11-11-large.png
A6: astrocartography | B6: 5 | C6: Intro 6 | D6: Medium | E6: [UI/UX][Intro 6] Button Continue hiển thị enabled khi chưa chọn ngày sinh, không đồng nhất với các màn input khác | F6: Fixed | G6: - Khi Month/Day/Year trống, button Continue hiển thị disabled (xám), đồng nhất với Intro 7, 8, 10, 12, 15. | H6: Screenshot/Video: screens/06-6-small.png, screens/06-6-large.png
A7: astrocartography | B7: 6 | C7: Intro 7 | D7: Medium | E7: [UI][Intro 7] Field Time of birth hiển thị hai icon đồng hồ | F7: Fixed | G7: - Field Time of birth chỉ còn một icon đồng hồ bên trái. | H7: Screenshot/Video: screens/07-7-small.png, screens/07-7-large.png
A8: astrocartography | B8: 7 | C8: Intro 9 | D8: Medium | E8: [UI][Responsive][Intro 9] Map card bị thu thấp và cắt mất phần dưới bản đồ trên màn hình nhỏ | F8: Fixed | G8: - Trên small map card hiển thị đủ chiều cao (thấy Nam Mỹ, Úc), màn cho cuộn để xem promise rows, cùng tỉ lệ với large. | H8: Screenshot/Video: screens/09-9-small-p1.png, screens/09-9-small-p2.png, screens/09-9-large.png
A9: astrocartography | B9: 8 | C9: Intro 14 | D9: Medium | E9: [UI][Intro 14] Các image card hiển thị viền màu khác nhau khi chưa chọn | F9: Fixed | G9: - 4 image card Big city / Coast / Mountains / Small town dùng chung viền xám mặc định khi chưa chọn, giống option "Other". | H9: Screenshot/Video: screens/14-14-small.png, screens/14-14-large.png
A10: astrocartography | B10: 9 | C10: Intro 15 | D10: Medium | E10: [UI][Responsive][Intro 15] Option "Anywhere" bị footer che và microcopy bị đẩy xuống dưới fold trên màn hình nhỏ | F10: Fixed | G10: - Trên small cả 4 option, microcopy "Your full map still covers the whole world." và "Pick at least one" + Continue đều nằm trong viewport, không bị che. | H10: Screenshot/Video: screens/15-15-small.png, screens/15-15-large.png
A11: astrocartography | B11: 10 | C11: Intro 18 | D11: Low | E11: [UI][Intro 18] Màn không có back button và progress bar, nội dung sát mép trên, không đồng nhất header | F11: Fixed | G11: - Intro 18 và 19 đã có khoảng đệm bằng chiều cao header phía trên, title không còn sát mép trên. Hai màn vẫn không có back button/progress bar (màn kết quả) – Spec chưa định nghĩa, nếu PM muốn có header đầy đủ thì log riêng. | H11: Screenshot/Video: screens/18-18-small-p1.png, screens/18-18-large.png, screens/19-19-small.png, screens/19-19-large.png
A12: astrocartography | B12: 11 | C12: Intro 19 | D12: Low | E12: [UI][Intro 19] Hiển thị dòng copy "Shown only because a line truly falls within 600 miles..." không có trong spec | F12: Fixed | G12: - Dòng "Shown only because a line truly falls within 600 miles..." đã bị bỏ, màn chỉ còn Headline, Body và một meaning card theo brief. | H12: Screenshot/Video: screens/19-19-small.png, screens/19-19-large.png
A13: astrocartography | B13: 12 | C13: Paywall 1 | D13: High | E13: [UI][Responsive][Paywall 1] CTA "Unlock my map" bị cắt ở mép dưới viewport đầu trên màn hình nhỏ | F13: Fixed | G13: - Trên small 375×667, button "Unlock my map" trong plan block hiển thị trọn vẹn ở viewport đầu (cả deep-jump và walk thật). | H13: Screenshot/Video: screens/21-21-small-p1.png, screens/walk-end-21 (paywall).png, screens/21-21-large-p1.png
... A118: witch-power | B118: 8 | C118: Download App | D118: Medium | E118: [UI][Download App] Badge App Store / Google Play dùng icon generic, không phải logo chính thức | F118: Fixed | G118: Badge dùng logo Apple và Google Play chính thức. | H118: Screenshot/Video: screens/24-get_app-small.png, screens/24-get_app-large.png

Sheet Bug đang mở
A1: # | B1: Funnel | C1: Screen | D1: Severity | E1: Loại | F1: Title | G1: Actual Result | H1: Expected Result | I1: Attachment | J1: Status
A2: 1 | B2: astrocartography | C2: Intro 6 | D2: Low | E2: Bug mới | F2: [UI][Intro 6] Select Month/Day/Year không có chevron dropdown | G2: - 3 ô Month / Day / Year (id: 6) chỉ hiển thị placeholder, không có chevron hay affordance dropdown nào, trên cả small và large. Commit fix ghi "chevrons on date selects" và aura-tarot đã có chevron, nhưng astrocartography chưa được áp dụng nên không đồng nhất giữa các funnel Starlyn. Chưa log ở lượt 1. | H2: - Select ngày sinh hiển thị chevron dropdown giống các funnel Starlyn đã fix (vd. aura-tarot) – Cần đối chiếu Figma. | I2: Screenshot/Video: screens/06-6-small.png, screens/06-6-large.png | J2: New
A3: 2 | B3: astrocartography | C3: Intro 11 | D3: High | E3: Bug mới | F3: [Logic][Intro 11] Headline "Chicago sits between your lines" mâu thuẫn với card "Near Chicago: your Venus line" ở Intro 18 | G3: - Với data test (current city Chicago), Intro 11 (id: 11) hiển thị "Chicago sits between your lines" (nghĩa là không có line nào gần), nhưng map zoom của chính màn này vẫn vẽ một line chạy sát pin, và Intro 18 (id: 18) lại mở card "Near Chicago: your Venus line – Venus ASC · love and beauty come easier here...", nên user thấy hai kết quả trái ngược. Không phải regression: lỗi đã có từ lượt 1 nhưng bị sót. | H3: - Kết quả về line gần current city phải nhất quán giữa Intro 11 và Intro 18 (brief #11: 0 line thì "{{current_city}} sits between your lines"; brief #18: card mở "one real result (the line nearest home)"). Copy của #18 khi không có line trong orb – Spec chưa định nghĩa – cần PM confirm. | I3: Screenshot/Video: screens/11-11-small.png, screens/11-11-large.png, screens/18-18-small-p1.png, screens/18-18-large.png | J3: New
A4: 3 | B4: astrocartography | C4: Intro 20 | D4: Low | E4: Bug mới | F4: [UI][Intro 20] Dấu chấm cuối dòng legal bị tách khỏi link "Privacy Policy" | G4: - Sau khi tăng vùng bấm của link legal, dòng "By continuing, you agree to our Terms & Privacy Policy." ở Intro 20 (id: 20) hiển thị dấu "." cách hẳn chữ "Policy" ("Privacy Policy ."); khoảng cách quanh "&" ở Intro 1 (id: 1) và Intro 20 cũng rộng hơn khoảng cách chữ bình thường. Regression nhỏ từ fix bug #1. | H4: - Dấu chấm liền sau "Policy" và khoảng cách quanh "&" như text thường, vùng bấm 44px không làm thay đổi spacing của dòng chữ (như cách aura-tarot giữ nguyên dòng) – Cần Designer confirm. | I4: Screenshot/Video: screens/20-20-small.png, screens/20-20-large.png, screens/01-1-small.png | J4: New
A5: 4 | B5: aura-tarot | C5: Intro 2 | D5: Low | E5: Bug mới | F5: [UI][Intro 2] Headline nằm sát progress bar mới, gần như không có khoảng cách | G5: - Progress bar mới thêm ở header nằm ngay trên headline, khoảng cách chỉ ~6–8pt (vd. "How do you feel right now?", "Which color pulls you in?", "When were you born?", "Pick three cards"), trên mọi màn có header Intro 2–7, 9–12, 16–18, cả small và large; nhìn chật so với khoảng cách headline–body bên dưới. | H5: - Có khoảng cách rõ giữa progress bar và headline – Cần đối chiếu Figma (giá trị spacing). | I5: Screenshot/Video: screens/02-energy_now-small.png, screens/02-energy_now-large.png, screens/09-color_pull-small.png, screens/11-birth_date-small.png, screens/16-pull-small.png | J5: New
A6: 5 | B6: aura-tarot | C6: Intro 8 | D6: Medium | E6: Bug mới | F6: [UI/UX][Intro 8] Progress bar nhảy lên 100% ở màn bridge rồi tụt về 7/10 ở màn sau | G6: - Intro 7 hiển thị "6/10" (bar ~60%), Intro 8 "Your colors are showing" hiển thị progress bar full 100% và không có bộ đếm, sang Intro 9 bar tụt về ~70% với "7/10", khiến user tưởng đã xong rồi lại bị lùi. Chọn Medium thay vì High vì màn bridge không hiển thị số đếm. | H6: - Progress bar tăng dần liên tục giữa các màn (vd. giữ ~60–65% hoặc ẩn bar ở màn bridge) – Spec chưa định nghĩa – cần PM/Designer confirm. | I6: Screenshot/Video: screens/07-crave-small.png, screens/08-bridge-small.png, screens/08-bridge-large.png, screens/09-color_pull-small.png | J6: New
A7: 6 | B7: aura-tarot | C7: Intro 9 | D7: Medium | E7: Bug cũ | F7: [UI][Intro 9] Các orb màu chưa chọn bị cắt vuông 4 cạnh và có vệt tối hình lưỡi liềm | G7: - Retest lượt 2: vệt tối lưỡi liềm đã gần hết, nhưng 5 orb chưa chọn (Red, Amber, Green, Blue, Violet) ở màn chọn màu (id: color_pull) vẫn bị cắt phẳng ở mép trái/phải/trên/dưới, không tròn trọn vẹn; chỉ orb đang chọn (Indigo, viền vàng) tròn đúng. Xảy ra cả small và large. | H7: - Theo Spec #9: "Six large color orbs ... each glowing softly in its own color" – mọi orb cần hiển thị tròn trọn vẹn với glow mềm, không bị cắt. | I7: Screenshot/Video: screens/09-color_pull-small.png, screens/09-color_pull-large.png | J7: Partly fixed
A8: 7 | B8: aura-tarot | C8: Intro 19 | D8: Medium | E8: Bug cũ | F8: [UI][Intro 19] Ảnh hero vẫn còn 2 đường kẻ dọc mờ ở mép trái/phải (bug cũ #1) | G8: - Retest lượt 2: khung/viền lạ ở Intro 1 và Intro 14 đã hết, nhưng ảnh hero Intro 19 (id: teaser) vẫn còn 2 đường kẻ dọc mảnh, mờ ở mép trái và mép phải ảnh, cả small và large; Intro 14 còn một vệt dọc rất mờ ở mép phải. | H8: - Ảnh hero chỉ hiển thị halo quanh silhouette trên nền sao, không có đường kẻ/khung lạ (Spec Visual #14, #19). Cần đối chiếu Figma. | I8: Screenshot/Video: screens/01-hook-small.png, screens/01-hook-large.png, screens/14-aura_reveal-large.png, screens/19-teaser-large.png, screens/19-teaser-small-p1.png | J8: Partly fixed
A9: 8 | B9: aura-tarot | C9: Paywall 1 | D9: High | E9: Bug cũ | F9: [UI][Paywall 1] Footer thiếu thông tin entity (tên pháp nhân) | G9: - Footer chỉ hiển thị "Terms of Use", "Privacy Policy", "Subscription terms", "Support: support@starlyn.co" và "For entertainment purposes only."; không thấy tên pháp nhân/entity. | H9: - Theo Spec #20 mục 9: "Footer: legal links, entity, entertainment disclaimer." Cần PM confirm nếu entity đang ẩn do chưa cấu hình. | I9: Screenshot/Video: screens/20-paywall-small-p4.png, screens/20-paywall-large-p4.png | J9: Cần PM
A10: 9 | B10: aura-tarot | C10: Upsale 1 | D10: Low | E10: Bug mới | F10: [UI][Responsive][Upsale 1] Microcopy dưới report card bị đẩy xuống dưới CTA trên màn hình nhỏ | G10: - Trên small 375×667, ở viewport đầu dòng "Paid once through secure checkout. No subscription." dưới report card không hiển thị (CTA "Add for $19.99" nằm ngay dưới card), chỉ thấy sau khi cuộn; trên large dòng này hiển thị ngay dưới card. Low vì price row đã có "Paid once · no subscription". | H10: - Microcopy hiển thị dưới card (brief #21: Under the card) và thấy được ở viewport đầu trên màn nhỏ – Spec chưa định nghĩa cho màn nhỏ – cần PM/Designer confirm. | I10: Screenshot/Video: screens/21-report_upsell-small-p1.png, screens/21-report_upsell-small-p2.png, screens/21-report_upsell-large.png | J10: New
A11: 10 | B11: ex-compatibility | C11: Intro 2 | D11: Low | E11: Bug mới | F11: [UI][Intro 2] Counter "n/14" lệch ra ngoài mép phải progress bar mới, progress bar sát headline | G11: - Trên header các màn câu hỏi (Intro 2, 3, 5–13, 15–17), counter "1/14"…"14/14" có mép phải lệch ra ngoài mép phải của progress bar mới khoảng 7–8pt (progress bar và nội dung căn lề 20pt, counter chỉ cách mép màn ~12pt); progress bar cũng nằm khá sát headline bên dưới (~12pt), cả small và large. | H11: - Counter và progress bar cần căn cùng lề phải, có khoảng cách rõ giữa progress bar và headline – Cần đối chiếu Figma (giá trị spacing). | I11: Screenshot/Video: screens/02-gender-small.png, screens/02-gender-large.png, screens/12-contact-small.png, screens/17-fate_2-small.png | J11: New
A12: 11 | B12: ex-compatibility | C12: Paywall 1 | D12: High | E12: Bug cũ | F12: [UI][Paywall 1] Footer thiếu tên pháp nhân (entity) theo spec | G12: - [Lượt 2] Footer vẫn chỉ có "Terms of Use" · "Privacy Policy" · "Subscription terms" và "For entertainment purposes only.", chưa có tên pháp nhân. Đúng như dev báo, chờ PM cung cấp entity. | H12: - Theo spec mục 22 – section 9 "Footer: legal links, entity, entertainment disclaimer": footer cần hiển thị tên pháp nhân bên cạnh legal links và disclaimer. | I12: Screenshot/Video: screens/22-paywall-small-p4.png, screens/22-paywall-large-p4.png | J12: Cần PM
A13: 12 | B13: ex-compatibility | C13: Paywall 1 | D13: Low | E13: Bug mới | F13: [UI][Paywall 1] Ảnh hero hiển thị thành dải chữ nhật cắt cứng, wheel bị cắt phẳng ở đáy | G13: - Ảnh hero Paywall 1 hiển thị thành một dải chữ nhật full-width ngay dưới subtitle: cạnh trên có đường nối màu nền rõ (nền khối headline tối hơn nền ảnh) và cạnh dưới cắt phẳng ngang qua vạch chia của 2 wheel; tương tự ở hero Intro 20 (dưới header, đáy cắt phẳng qua wheel), cả small và large. Có thể đã tồn tại từ lượt 1 nhưng chưa được log. | H13: - Spec #22 Hero: "the two wheels" – ảnh hero cần fade mềm vào nền, không thấy cạnh cắt cứng/wheel bị cắt – Cần đối chiếu Figma (crop/fade của hero). | I13: Screenshot/Video: screens/22-paywall-small-p1.png, screens/22-paywall-large-p1.png, screens/20-result_teaser-small-p1.png, screens/20-result_teaser-large.png | J13: New
... A41: 40 | B41: witch-power | C41: Upsale 1 | D41: Medium | E41: Bug mới | F41: [UI][Responsive][Upsale 1] Report card bị vùng CTA cắt mép dưới, microcopy bị ẩn trên màn small | G41: - Trên 375x667 (id: report_upsell), mép dưới report card (ngay dưới dòng "$19.99 · Paid once · no subscription") bị vùng CTA "Add for $19.99" cắt ngang, mất viền và góc bo dưới của card; dòng "One-time payment at a secure checkout. No subscription." chỉ thấy khi cuộn (p2). Trên large card và microcopy hiển thị đầy đủ. | H41: - Card hiển thị đầy đủ, microcopy dưới card hiển thị như large (brief #23). | I41: Screenshot/Video: screens/23-report_upsell-small-p1.png, screens/23-report_upsell-small-p2.png, screens/23-report_upsell-large.png | J41: New
