Workbook

Sheet Tổng quan
A1: Starlyn – UI test 10 funnel (06/10/2026)
A2: Test funnel.html local · 375×667 + 430×932 · data test test / test@gmail.com · Tester: Claude Code (skill qa-ui-test)
A3: Cả 10 funnel đi thật tới paywall không lỗi JS; product rules (Starlyn, 1 gói $13.67→$49.99/tháng, không X/sale, email-only, add-on $19.99, Download App) đều đúng.
A5: Funnel | B5: Critical | C5: High | D5: Medium | E5: Low | F5: Tổng | G5: Open | H5: [Logic] | I5: [UI/UX] | J5: [UI/UX][Responsive] | K5: [UI] | L5: [UI][Responsive]
A6: astrocartography | B6: =COUNTIFS('Bug List'!$B$2:$B$118,$A6,'Bug List'!$E$2:$E$118,B$5) | C6: =COUNTIFS('Bug List'!$B$2:$B$118,$A6,'Bug List'!$E$2:$E$118,C$5) | D6: =COUNTIFS('Bug List'!$B$2:$B$118,$A6,'Bug List'!$E$2:$E$118,D$5) | E6: =COUNTIFS('Bug List'!$B$2:$B$118,$A6,'Bug List'!$E$2:$E$118,E$5) | F6: =COUNTIF('Bug List'!$B$2:$B$118,$A6) | G6: =COUNTIFS('Bug List'!$B$2:$B$118,$A6,'Bug List'!$J$2:$J$118,"Open") | H6: =COUNTIFS('Bug List'!$B$2:$B$118,$A6,'Bug List'!$D$2:$D$118,H$5) | I6: =COUNTIFS('Bug List'!$B$2:$B$118,$A6,'Bug List'!$D$2:$D$118,I$5) | J6: =COUNTIFS('Bug List'!$B$2:$B$118,$A6,'Bug List'!$D$2:$D$118,J$5) | K6: =COUNTIFS('Bug List'!$B$2:$B$118,$A6,'Bug List'!$D$2:$D$118,K$5) | L6: =COUNTIFS('Bug List'!$B$2:$B$118,$A6,'Bug List'!$D$2:$D$118,L$5)
A7: aura-tarot | B7: =COUNTIFS('Bug List'!$B$2:$B$118,$A7,'Bug List'!$E$2:$E$118,B$5) | C7: =COUNTIFS('Bug List'!$B$2:$B$118,$A7,'Bug List'!$E$2:$E$118,C$5) | D7: =COUNTIFS('Bug List'!$B$2:$B$118,$A7,'Bug List'!$E$2:$E$118,D$5) | E7: =COUNTIFS('Bug List'!$B$2:$B$118,$A7,'Bug List'!$E$2:$E$118,E$5) | F7: =COUNTIF('Bug List'!$B$2:$B$118,$A7) | G7: =COUNTIFS('Bug List'!$B$2:$B$118,$A7,'Bug List'!$J$2:$J$118,"Open") | H7: =COUNTIFS('Bug List'!$B$2:$B$118,$A7,'Bug List'!$D$2:$D$118,H$5) | I7: =COUNTIFS('Bug List'!$B$2:$B$118,$A7,'Bug List'!$D$2:$D$118,I$5) | J7: =COUNTIFS('Bug List'!$B$2:$B$118,$A7,'Bug List'!$D$2:$D$118,J$5) | K7: =COUNTIFS('Bug List'!$B$2:$B$118,$A7,'Bug List'!$D$2:$D$118,K$5) | L7: =COUNTIFS('Bug List'!$B$2:$B$118,$A7,'Bug List'!$D$2:$D$118,L$5)
A8: ex-compatibility | B8: =COUNTIFS('Bug List'!$B$2:$B$118,$A8,'Bug List'!$E$2:$E$118,B$5) | C8: =COUNTIFS('Bug List'!$B$2:$B$118,$A8,'Bug List'!$E$2:$E$118,C$5) | D8: =COUNTIFS('Bug List'!$B$2:$B$118,$A8,'Bug List'!$E$2:$E$118,D$5) | E8: =COUNTIFS('Bug List'!$B$2:$B$118,$A8,'Bug List'!$E$2:$E$118,E$5) | F8: =COUNTIF('Bug List'!$B$2:$B$118,$A8) | G8: =COUNTIFS('Bug List'!$B$2:$B$118,$A8,'Bug List'!$J$2:$J$118,"Open") | H8: =COUNTIFS('Bug List'!$B$2:$B$118,$A8,'Bug List'!$D$2:$D$118,H$5) | I8: =COUNTIFS('Bug List'!$B$2:$B$118,$A8,'Bug List'!$D$2:$D$118,I$5) | J8: =COUNTIFS('Bug List'!$B$2:$B$118,$A8,'Bug List'!$D$2:$D$118,J$5) | K8: =COUNTIFS('Bug List'!$B$2:$B$118,$A8,'Bug List'!$D$2:$D$118,K$5) | L8: =COUNTIFS('Bug List'!$B$2:$B$118,$A8,'Bug List'!$D$2:$D$118,L$5)
A9: marriage-compatibility | B9: =COUNTIFS('Bug List'!$B$2:$B$118,$A9,'Bug List'!$E$2:$E$118,B$5) | C9: =COUNTIFS('Bug List'!$B$2:$B$118,$A9,'Bug List'!$E$2:$E$118,C$5) | D9: =COUNTIFS('Bug List'!$B$2:$B$118,$A9,'Bug List'!$E$2:$E$118,D$5) | E9: =COUNTIFS('Bug List'!$B$2:$B$118,$A9,'Bug List'!$E$2:$E$118,E$5) | F9: =COUNTIF('Bug List'!$B$2:$B$118,$A9) | G9: =COUNTIFS('Bug List'!$B$2:$B$118,$A9,'Bug List'!$J$2:$J$118,"Open") | H9: =COUNTIFS('Bug List'!$B$2:$B$118,$A9,'Bug List'!$D$2:$D$118,H$5) | I9: =COUNTIFS('Bug List'!$B$2:$B$118,$A9,'Bug List'!$D$2:$D$118,I$5) | J9: =COUNTIFS('Bug List'!$B$2:$B$118,$A9,'Bug List'!$D$2:$D$118,J$5) | K9: =COUNTIFS('Bug List'!$B$2:$B$118,$A9,'Bug List'!$D$2:$D$118,K$5) | L9: =COUNTIFS('Bug List'!$B$2:$B$118,$A9,'Bug List'!$D$2:$D$118,L$5)
A10: moon-reading | B10: =COUNTIFS('Bug List'!$B$2:$B$118,$A10,'Bug List'!$E$2:$E$118,B$5) | C10: =COUNTIFS('Bug List'!$B$2:$B$118,$A10,'Bug List'!$E$2:$E$118,C$5) | D10: =COUNTIFS('Bug List'!$B$2:$B$118,$A10,'Bug List'!$E$2:$E$118,D$5) | E10: =COUNTIFS('Bug List'!$B$2:$B$118,$A10,'Bug List'!$E$2:$E$118,E$5) | F10: =COUNTIF('Bug List'!$B$2:$B$118,$A10) | G10: =COUNTIFS('Bug List'!$B$2:$B$118,$A10,'Bug List'!$J$2:$J$118,"Open") | H10: =COUNTIFS('Bug List'!$B$2:$B$118,$A10,'Bug List'!$D$2:$D$118,H$5) | I10: =COUNTIFS('Bug List'!$B$2:$B$118,$A10,'Bug List'!$D$2:$D$118,I$5) | J10: =COUNTIFS('Bug List'!$B$2:$B$118,$A10,'Bug List'!$D$2:$D$118,J$5) | K10: =COUNTIFS('Bug List'!$B$2:$B$118,$A10,'Bug List'!$D$2:$D$118,K$5) | L10: =COUNTIFS('Bug List'!$B$2:$B$118,$A10,'Bug List'!$D$2:$D$118,L$5)
A11: palm-reading | B11: =COUNTIFS('Bug List'!$B$2:$B$118,$A11,'Bug List'!$E$2:$E$118,B$5) | C11: =COUNTIFS('Bug List'!$B$2:$B$118,$A11,'Bug List'!$E$2:$E$118,C$5) | D11: =COUNTIFS('Bug List'!$B$2:$B$118,$A11,'Bug List'!$E$2:$E$118,D$5) | E11: =COUNTIFS('Bug List'!$B$2:$B$118,$A11,'Bug List'!$E$2:$E$118,E$5) | F11: =COUNTIF('Bug List'!$B$2:$B$118,$A11) | G11: =COUNTIFS('Bug List'!$B$2:$B$118,$A11,'Bug List'!$J$2:$J$118,"Open") | H11: =COUNTIFS('Bug List'!$B$2:$B$118,$A11,'Bug List'!$D$2:$D$118,H$5) | I11: =COUNTIFS('Bug List'!$B$2:$B$118,$A11,'Bug List'!$D$2:$D$118,I$5) | J11: =COUNTIFS('Bug List'!$B$2:$B$118,$A11,'Bug List'!$D$2:$D$118,J$5) | K11: =COUNTIFS('Bug List'!$B$2:$B$118,$A11,'Bug List'!$D$2:$D$118,K$5) | L11: =COUNTIFS('Bug List'!$B$2:$B$118,$A11,'Bug List'!$D$2:$D$118,L$5)
A12: past-life | B12: =COUNTIFS('Bug List'!$B$2:$B$118,$A12,'Bug List'!$E$2:$E$118,B$5) | C12: =COUNTIFS('Bug List'!$B$2:$B$118,$A12,'Bug List'!$E$2:$E$118,C$5) | D12: =COUNTIFS('Bug List'!$B$2:$B$118,$A12,'Bug List'!$E$2:$E$118,D$5) | E12: =COUNTIFS('Bug List'!$B$2:$B$118,$A12,'Bug List'!$E$2:$E$118,E$5) | F12: =COUNTIF('Bug List'!$B$2:$B$118,$A12) | G12: =COUNTIFS('Bug List'!$B$2:$B$118,$A12,'Bug List'!$J$2:$J$118,"Open") | H12: =COUNTIFS('Bug List'!$B$2:$B$118,$A12,'Bug List'!$D$2:$D$118,H$5) | I12: =COUNTIFS('Bug List'!$B$2:$B$118,$A12,'Bug List'!$D$2:$D$118,I$5) | J12: =COUNTIFS('Bug List'!$B$2:$B$118,$A12,'Bug List'!$D$2:$D$118,J$5) | K12: =COUNTIFS('Bug List'!$B$2:$B$118,$A12,'Bug List'!$D$2:$D$118,K$5) | L12: =COUNTIFS('Bug List'!$B$2:$B$118,$A12,'Bug List'!$D$2:$D$118,L$5)
A13: soulmate-sketch | B13: =COUNTIFS('Bug List'!$B$2:$B$118,$A13,'Bug List'!$E$2:$E$118,B$5) | C13: =COUNTIFS('Bug List'!$B$2:$B$118,$A13,'Bug List'!$E$2:$E$118,C$5) | D13: =COUNTIFS('Bug List'!$B$2:$B$118,$A13,'Bug List'!$E$2:$E$118,D$5) | E13: =COUNTIFS('Bug List'!$B$2:$B$118,$A13,'Bug List'!$E$2:$E$118,E$5) | F13: =COUNTIF('Bug List'!$B$2:$B$118,$A13) | G13: =COUNTIFS('Bug List'!$B$2:$B$118,$A13,'Bug List'!$J$2:$J$118,"Open") | H13: =COUNTIFS('Bug List'!$B$2:$B$118,$A13,'Bug List'!$D$2:$D$118,H$5) | I13: =COUNTIFS('Bug List'!$B$2:$B$118,$A13,'Bug List'!$D$2:$D$118,I$5) | J13: =COUNTIFS('Bug List'!$B$2:$B$118,$A13,'Bug List'!$D$2:$D$118,J$5) | K13: =COUNTIFS('Bug List'!$B$2:$B$118,$A13,'Bug List'!$D$2:$D$118,K$5) | L13: =COUNTIFS('Bug List'!$B$2:$B$118,$A13,'Bug List'!$D$2:$D$118,L$5)
A14: tarot | B14: =COUNTIFS('Bug List'!$B$2:$B$118,$A14,'Bug List'!$E$2:$E$118,B$5) | C14: =COUNTIFS('Bug List'!$B$2:$B$118,$A14,'Bug List'!$E$2:$E$118,C$5) | D14: =COUNTIFS('Bug List'!$B$2:$B$118,$A14,'Bug List'!$E$2:$E$118,D$5) | E14: =COUNTIFS('Bug List'!$B$2:$B$118,$A14,'Bug List'!$E$2:$E$118,E$5) | F14: =COUNTIF('Bug List'!$B$2:$B$118,$A14) | G14: =COUNTIFS('Bug List'!$B$2:$B$118,$A14,'Bug List'!$J$2:$J$118,"Open") | H14: =COUNTIFS('Bug List'!$B$2:$B$118,$A14,'Bug List'!$D$2:$D$118,H$5) | I14: =COUNTIFS('Bug List'!$B$2:$B$118,$A14,'Bug List'!$D$2:$D$118,I$5) | J14: =COUNTIFS('Bug List'!$B$2:$B$118,$A14,'Bug List'!$D$2:$D$118,J$5) | K14: =COUNTIFS('Bug List'!$B$2:$B$118,$A14,'Bug List'!$D$2:$D$118,K$5) | L14: =COUNTIFS('Bug List'!$B$2:$B$118,$A14,'Bug List'!$D$2:$D$118,L$5)
A15: witch-power | B15: =COUNTIFS('Bug List'!$B$2:$B$118,$A15,'Bug List'!$E$2:$E$118,B$5) | C15: =COUNTIFS('Bug List'!$B$2:$B$118,$A15,'Bug List'!$E$2:$E$118,C$5) | D15: =COUNTIFS('Bug List'!$B$2:$B$118,$A15,'Bug List'!$E$2:$E$118,D$5) | E15: =COUNTIFS('Bug List'!$B$2:$B$118,$A15,'Bug List'!$E$2:$E$118,E$5) | F15: =COUNTIF('Bug List'!$B$2:$B$118,$A15) | G15: =COUNTIFS('Bug List'!$B$2:$B$118,$A15,'Bug List'!$J$2:$J$118,"Open") | H15: =COUNTIFS('Bug List'!$B$2:$B$118,$A15,'Bug List'!$D$2:$D$118,H$5) | I15: =COUNTIFS('Bug List'!$B$2:$B$118,$A15,'Bug List'!$D$2:$D$118,I$5) | J15: =COUNTIFS('Bug List'!$B$2:$B$118,$A15,'Bug List'!$D$2:$D$118,J$5) | K15: =COUNTIFS('Bug List'!$B$2:$B$118,$A15,'Bug List'!$D$2:$D$118,K$5) | L15: =COUNTIFS('Bug List'!$B$2:$B$118,$A15,'Bug List'!$D$2:$D$118,L$5)
A16: Tổng | B16: =SUM(B6:B15) | C16: =SUM(C6:C15) | D16: =SUM(D6:D15) | E16: =SUM(E6:E15) | F16: =SUM(F6:F15) | G16: =SUM(G6:G15) | H16: =SUM(H6:H15) | I16: =SUM(I6:I15) | ... L16: =SUM(L6:L15)

Sheet Bug List
A1: # | B1: Funnel | C1: Screen | D1: Bug Type | E1: Severity | F1: Title | G1: Actual Result | H1: Expected Result | I1: Screenshot (đã xoá, tên file để tham chiếu) | J1: Status
A2: 1 | B2: astrocartography | C2: Intro 1 | D2: [UI/UX] | E2: High | F2: [UI/UX][Intro 1] Link "Terms" và "Privacy Policy" có tap target quá nhỏ | G2: - Ở dòng legal "By continuing, you agree to our Terms & Privacy Policy" (id: 1) và dưới button Continue ở Intro 20 (id: 20), vùng bấm của link "Terms" chỉ khoảng 35x15 và "Privacy Policy" khoảng 79x15 (đo tự động), trên cả small và large. | H2: - Tap target tối thiểu 44pt theo Apple HIG – cần Designer confirm. | I2: screens/01-1-small.png, screens/01-1-large.png, screens/20-20-small.png, screens/20-20-large.png | J2: Fixed
A3: 2 | B3: astrocartography | C3: Intro 1 | D3: [UI] | E3: Low | F3: [UI][Intro 1] Globe hero không hiển thị các planetary line màu theo spec | G3: - Globe 3D ở Intro 1 (id: 1) và Intro 17 (id: 17, loading) chỉ hiển thị chấm lục địa và viền glow vàng, không thấy line màu nào chạy qua globe, Intro 17 cũng không thấy city pin, trên cả small và large. | H3: - Intro 1: globe có ba line màu phát sáng chạy qua; Intro 17: line màu chạy từ cực này sang cực kia, có city pin sáng dần dọc theo line (Visual note trong brief #1, #17). Cần verify thêm vì có thể phụ thuộc thời điểm animation. | I3: screens/01-1-small.png, screens/01-1-large.png, screens/17-17-small.png, screens/17-17-large.png | J3: Partly fixed
A4: 3 | B4: astrocartography | C4: Intro 2 | D4: [UI] | E4: Medium | F4: [UI][Intro 2] Venus và Jupiter hiển thị cùng màu vàng, không phân biệt được line | G4: - Chip legend và line của Venus đang cùng tông vàng với Jupiter ở Intro 2 (id: 2), Intro 4 (id: 4), Intro 9 (id: 9) và trên map ở Intro 18 (id: 18), nên user không phân biệt được line Venus với line Jupiter trên map. | H4: - Venus dùng màu rose, Jupiter gold, Sun amber, Moon silver theo Visual note của brief #2, áp dụng đồng nhất cho legend và line trên mọi màn map. | I4: screens/02-2-small.png, screens/04-4-small.png, screens/09-9-small.png, screens/18-18-small-p1.png | J4: Fixed
A5: 4 | B5: astrocartography | C5: Intro 5 | D5: [UI] | E5: Medium | F5: [UI][Intro 5] Label trên map card nằm đè lên lưới chấm bản đồ | G5: - Label "test's map" (Intro 5, id: 5) và label "Chicago" (Intro 11, id: 11) nằm ở góc trên trái map card, đè trực tiếp lên các chấm vàng của bản đồ (Intro 11 còn đè lên cả line), nền label gần như trong suốt nên chữ bị lẫn với chấm phía sau. | H5: - Label không bị lẫn với nội dung map, đọc rõ – Cần đối chiếu Figma (vị trí/nền label). | I5: screens/05-5-small.png, screens/05-5-large.png, screens/11-11-small.png, screens/11-11-large.png | J5: Fixed
A6: 5 | B6: astrocartography | C6: Intro 6 | D6: [UI/UX] | E6: Medium | F6: [UI/UX][Intro 6] Button Continue hiển thị enabled khi chưa chọn ngày sinh, không đồng nhất với các màn input khác | G6: - Ở Intro 6 (id: 6), khi Month/Day/Year đều trống, button Continue vẫn hiển thị trạng thái enabled (màu vàng). Các màn input khác (Intro 7, 8, 10, 12, 15) hiển thị Continue disabled (xám) khi chưa nhập. | H6: - Spec chưa định nghĩa – cần PM/Designer confirm. (trạng thái button Continue khi input trống cần đồng nhất giữa các màn; brief #6 chỉ định nghĩa lỗi "Pick a full date to continue"). | I6: screens/06-6-small.png, screens/06-6-large.png, screens/07-7-small.png | J6: Fixed
A7: 6 | B7: astrocartography | C7: Intro 7 | D7: [UI] | E7: Medium | F7: [UI][Intro 7] Field Time of birth hiển thị hai icon đồng hồ | G7: - Field "Time of birth" (id: 7) hiển thị một icon đồng hồ ở bên trái và thêm một icon đồng hồ khác ở bên phải (icon picker mặc định của trình duyệt), trên cả small và large. | H7: - Field chỉ hiển thị một icon đồng hồ – Spec chưa định nghĩa – cần PM/Designer confirm. | I7: screens/07-7-small.png, screens/07-7-large.png | J7: Fixed
A8: 7 | B8: astrocartography | C8: Intro 9 | D8: [UI][Responsive] | E8: Medium | F8: [UI][Responsive][Intro 9] Map card bị thu thấp và cắt mất phần dưới bản đồ trên màn hình nhỏ | G8: - Trên small 375×667 (id: 9), map card dưới bảng vị trí hành tinh bị thu thấp, phần dưới bản đồ (Nam Mỹ, Úc) bị cắt. Trên large 430×932 map hiển thị đầy đủ. | H8: - Map hiển thị đủ nội dung, cùng tỉ lệ như trên large – Cần đối chiếu Figma. | I8: screens/09-9-small.png, screens/09-9-large.png | J8: Fixed
A9: 8 | B9: astrocartography | C9: Intro 14 | D9: [UI] | E9: Medium | F9: [UI][Intro 14] Các image card hiển thị viền màu khác nhau khi chưa chọn | G9: - Khi chưa chọn option nào (id: 14), 4 image card Big city / Coast / Mountains / Small town có viền gradient mỗi card một màu (vàng, cam, vàng-tím, xanh ngọc), nhìn giống selected state; option "Other" và option ở các màn khác dùng viền xám mặc định. | H9: - Option ở trạng thái default dùng chung một style viền, chỉ option được chọn mới highlight (brief #3: "purple border on select") – Cần đối chiếu Figma. | I9: screens/14-14-small.png, screens/14-14-large.png | J9: Fixed
A10: 9 | B10: astrocartography | C10: Intro 15 | D10: [UI][Responsive] | E10: Medium | F10: [UI][Responsive][Intro 15] Option "Anywhere" bị footer che và microcopy bị đẩy xuống dưới fold trên màn hình nhỏ | G10: - Trên small 375×667 (id: 15), option cuối "Anywhere" bị cắt ngang bởi vùng footer ("Pick at least one" + Continue); dòng "Your full map still covers the whole world." chỉ thấy sau khi cuộn. Trên large cả 4 option và microcopy hiển thị đủ. | H10: - Spec chưa định nghĩa – cần PM/Designer confirm. (option và microcopy không bị footer che trên màn hình nhỏ). | I10: screens/15-15-small-p1.png, screens/15-15-small-p2.png, screens/15-15-large.png | J10: Fixed
A11: 10 | B11: astrocartography | C11: Intro 18 | D11: [UI] | E11: Low | F11: [UI][Intro 18] Màn không có back button và progress bar, nội dung sát mép trên, không đồng nhất header | G11: - Intro 18 (id: 18) và Intro 19 (id: 19) không có back button và progress bar; title "test, your map is ready" / map card bắt đầu sát mép trên màn hình, trong khi các màn intro trước đều có hàng header (back + progress) phía trên nội dung. | H11: - Spec chưa định nghĩa – cần PM/Designer confirm. (header và khoảng cách phía trên cần đồng nhất giữa các màn). | I11: screens/18-18-small-p1.png, screens/18-18-large.png, screens/19-19-small.png, screens/19-19-large.png | J11: Fixed
A12: 11 | B12: astrocartography | C12: Intro 19 | D12: [UI] | E12: Low | F12: [UI][Intro 19] Hiển thị dòng copy "Shown only because a line truly falls within 600 miles..." không có trong spec | G12: - Màn "Why Seattle felt right" (id: 19) hiển thị dòng "Shown only because a line truly falls within 600 miles. We never invent a match." dưới card meaning. Brief #19 chỉ ghi điều kiện này như path rule nội bộ, không phải copy hiển thị. | H12: - Spec chưa định nghĩa – cần PM/Designer confirm. (copy hiển thị trên Intro 19 cần bám theo brief: Headline, Body và một meaning card). | I12: screens/19-19-small.png, screens/19-19-large.png | J12: Fixed
A13: 12 | B13: astrocartography | C13: Paywall 1 | D13: [UI][Responsive] | E13: High | F13: [UI][Responsive][Paywall 1] CTA "Unlock my map" bị cắt ở mép dưới viewport đầu trên màn hình nhỏ | G13: - Trên small 375×667, khi vào Paywall (id: 21) thì button "Unlock my map" trong plan block chỉ hiện nửa trên ở mép dưới màn hình, chưa có sticky CTA (header chưa có mini CTA); user phải cuộn mới thấy đủ button. Trên large button hiển thị đầy đủ. | H13: - Spec chưa định nghĩa – cần PM/Designer confirm. (CTA cần hiển thị trọn vẹn trong viewport đầu hoặc có sticky CTA thay thế). | I13: screens/21-21-small-p1.png, screens/walk-end-21 (paywall).png, screens/21-21-large-p1.png | J13: Fixed
... A118: 117 | B118: witch-power | C118: Download App | D118: [UI] | E118: Medium | F118: [UI][Download App] Badge App Store / Google Play dùng icon generic, không phải logo chính thức | G118: - Ở màn Download App, badge "Download on the App Store" hiển thị icon dạng outline giống chiếc răng thay vì logo Apple; badge "Get it on Google Play" chỉ là tam giác outline thay vì logo Google Play. | H118: - Spec yêu cầu "App Store and Google Play badges" – hiển thị badge chính thức theo brand guideline của Apple/Google; cần Designer confirm asset. | I118: screens/24-get_app-small.png, screens/24-get_app-large.png | J118: Fixed

Sheet Lỗi chung
A1: Lỗi chung (sửa 1 lần ở engine) | B1: Severity | C1: Funnel bị ảnh hưởng
A2: Terms / Privacy ở màn Hook + Email quá nhỏ để bấm hoặc là text thường không phải link | B2: High | C2: astro, moon, palm, soulmate (nhỏ); aura, ex, marriage, past-life (không phải link)
A3: Footer paywall thiếu tên pháp nhân (legal_entity còn placeholder) | B3: High | C3: aura, ex, marriage, palm, past-life, witch-power
A4: Badge App Store / Google Play ở Download App là icon tự vẽ, không phải badge chính thức | B4: Medium | C4: aura, ex, marriage, moon, palm, past-life, tarot, witch-power
A5: Ô giờ sinh có 2 icon đồng hồ (custom + native input time) | B5: Medium | C5: moon, astro, soulmate
A6: Sticky bar paywall trong suốt, chữ phía sau lộ ra (header frosted cần Designer confirm) | B6: Medium / Low | C6: moon, astro (bottom bar); past-life, soulmate (header)
A7: "Due today … $13.67 today" lặp chữ "today" | B7: Low | C7: ex, marriage, aura
A8: Select Month/Day/Year không có chevron | B8: Low | C8: palm, aura, past-life, soulmate
A9: Loader / màn kết quả thiếu header, title sát mép trên | B9: Low | C9: moon, palm, ex, marriage, astro, soulmate
A10: Đã loại: "sticky CTA bị cắt mép dưới màn small" — do chụp lúc animation, chụp lại sau 2s CTA hiện đủ | B10: — | C10: aura, palm, past-life
